py_metarium_encoder/__init__.py
py_metarium_encoder/substrate/__init__.py
py_metarium_encoder/substrate/base.py
py_metarium_encoder/substrate/data_custodian/__init__.py
py_metarium_encoder/substrate/data_custodian/base.py
py_metarium_encoder/substrate/data_custodian/root.py
py_metarium_encoder/substrate/scribe/__init__.py
py_metarium_encoder/substrate/scribe/base.py
py_metarium_encoder/substrate/scribe/root.py
py_metarium_encoder/substrate/topic/__init__.py
py_metarium_encoder/substrate/topic/committer_node.py
py_metarium_encoder/substrate/topic/configuration_node.py
py_metarium_encoder/substrate/topic/data_custodian.py
py_metarium_encoder/substrate/topic/hasher.py
py_metarium_encoder/substrate/topic/listener_node.py
py_metarium_encoder/utils/__init__.py
py_metarium_encoder/utils/exceptions.py
py_metarium_encoder-0.0.1.62.dist-info/LICENSE
py_metarium_encoder-0.0.1.62.dist-info/METADATA
py_metarium_encoder-0.0.1.62.dist-info/WHEEL
py_metarium_encoder-0.0.1.62.dist-info/top_level.txt
py_metarium_encoder-0.0.1.62.dist-info/RECORD
